{
  "data": [
    {
      "direction_color": "redFont",
      "rowDate": "2008年12月31日",
      "rowDateRaw": 1230681600,
      "rowDateTimestamp": "2008-12-31T00:00:00Z",
      "last_close": "1,817.72",
      "last_open": "1,835.11",
      "last_max": "1,844.42",
      "last_min": "1,813.73",
      "volume": "35.63K",
      "volumeRaw": 35631,
      "change_precent": "-0.86",
      "last_closeRaw": "1817.71997070312500",
      "last_openRaw": "1835.10998535156250",
      "last_maxRaw": "1844.42004394531250",
      "last_minRaw": "1813.72998046875000",
      "change_precentRaw": -0.8568684131698752
    },
    {
      "direction_color": "redFont",
      "rowDate": "2008年12月30日",
      "rowDateRaw": 1230595200,
      "rowDateTimestamp": "2008-12-30T00:00:00Z",
      "last_close": "1,833.43",
      "last_open": "1,852.95",
      "last_max": "1,867.41",
      "last_min": "1,824.53",
      "volume": "37.59K",
      "volumeRaw": 37585,
      "change_precent": "-1.15",
      "last_closeRaw": "1833.43005371093750",
      "last_openRaw": "1852.94995117187500",
      "last_maxRaw": "1867.41003417968750",
      "last_minRaw": "1824.53002929687500",
      "change_precentRaw": -1.1500116426050635
    },
    {
      "direction_color": "redFont",
      "rowDate": "2008年12月29日",
      "rowDateRaw": 1230508800,
      "rowDateTimestamp": "2008-12-29T00:00:00Z",
      "last_close": "1,854.76",
      "last_open": "1,852.41",
      "last_max": "1,861.30",
      "last_min": "1,816.06",
      "volume": "35.99K",
      "volumeRaw": 35987,
      "change_precent": "-0.39",
      "last_closeRaw": "1854.76000976562500",
      "last_openRaw": "1852.41003417968750",
      "last_maxRaw": "1861.30004882812500",
      "last_minRaw": "1816.06005859375000",
      "change_precentRaw": -0.3941767851644416
    },
    {
      "direction_color": "redFont",
      "rowDate": "2008年12月26日",
      "rowDateRaw": 1230249600,
      "rowDateTimestamp": "2008-12-26T00:00:00Z",
      "last_close": "1,862.10",
      "last_open": "1,868.34",
      "last_max": "1,881.08",
      "last_min": "1,850.50",
      "volume": "34.56K",
      "volumeRaw": 34561,
      "change_precent": "-0.46",
      "last_closeRaw": "1862.09997558593750",
      "last_openRaw": "1868.33996582031250",
      "last_maxRaw": "1881.07995605468750",
      "last_minRaw": "1850.50000000000000",
      "change_precentRaw": -0.46344787733368276
    },
    {
      "direction_color": "redFont",
      "rowDate": "2008年12月25日",
      "rowDateRaw": 1230163200,
      "rowDateTimestamp": "2008-12-25T00:00:00Z",
      "last_close": "1,870.77",
      "last_open": "1,891.53",
      "last_max": "1,902.71",
      "last_min": "1,848.71",
      "volume": "39.92K",
      "volumeRaw": 39917,
      "change_precent": "-0.86",
      "last_closeRaw": "1870.77001953125000",
      "last_openRaw": "1891.53002929687500",
      "last_maxRaw": "1902.70996093750000",
      "last_minRaw": "1848.70996093750000",
      "change_precentRaw": -0.8642949373240462
    },
    {
      "direction_color": "redFont",
      "rowDate": "2008年12月24日",
      "rowDateRaw": 1230076800,
      "rowDateTimestamp": "2008-12-24T00:00:00Z",
      "last_close": "1,887.08",
      "last_open": "1,893.22",
      "last_max": "1,912.78",
      "last_min": "1,872.65",
      "volume": "44.20K",
      "volumeRaw": 44202,
      "change_precent": "-1.66",
      "last_closeRaw": "1887.07995605468750",
      "last_openRaw": "1893.21997070312500",
      "last_maxRaw": "1912.78002929687500",
      "last_minRaw": "1872.65002441406250",
      "change_precentRaw": -1.660803873374861
    },
    {
      "direction_color": "redFont",
      "rowDate": "2008年12月23日",
      "rowDateRaw": 1229990400,
      "rowDateTimestamp": "2008-12-23T00:00:00Z",
      "last_close": "1,918.95",
      "last_open": "2,019.23",
      "last_max": "2,019.23",
      "last_min": "1,918.43",
      "volume": "63.59K",
      "volumeRaw": 63590,
      "change_precent": "-4.89",
      "last_closeRaw": "1918.94995117187500",
      "last_openRaw": "2019.22998046875000",
      "last_maxRaw": "2019.22998046875000",
      "last_minRaw": "1918.43005371093750",
      "change_precentRaw": -4.887120283014587
    },
    {
      "direction_color": "redFont",
      "rowDate": "2008年12月22日",
      "rowDateRaw": 1229904000,
      "rowDateTimestamp": "2008-12-22T00:00:00Z",
      "last_close": "2,017.55",
      "last_open": "2,050.77",
      "last_max": "2,055.37",
      "last_min": "1,993.33",
      "volume": "52.95K",
      "volumeRaw": 52949,
      "change_precent": "-1.68",
      "last_closeRaw": "2017.55004882812500",
      "last_openRaw": "2050.77001953125000",
      "last_maxRaw": "2055.37011718750000",
      "last_minRaw": "1993.32995605468750",
      "change_precentRaw": -1.6841230140993164
    },
    {
      "direction_color": "greenFont",
      "rowDate": "2008年12月19日",
      "rowDateRaw": 1229644800,
      "rowDateTimestamp": "2008-12-19T00:00:00Z",
      "last_close": "2,052.11",
      "last_open": "2,037.37",
      "last_max": "2,075.38",
      "last_min": "2,033.11",
      "volume": "63.31K",
      "volumeRaw": 63311,
      "change_precent": "0.34",
      "last_closeRaw": "2052.11010742187500",
      "last_openRaw": "2037.36999511718750",
      "last_maxRaw": "2075.37988281250000",
      "last_minRaw": "2033.10998535156250",
      "change_precentRaw": 0.34277697519061584
    },
    {
      "direction_color": "greenFont",
      "rowDate": "2008年12月18日",
      "rowDateRaw": 1229558400,
      "rowDateTimestamp": "2008-12-18T00:00:00Z",
      "last_close": "2,045.10",
      "last_open": "2,001.05",
      "last_max": "2,045.94",
      "last_min": "1,982.43",
      "volume": "58.43K",
      "volumeRaw": 58429,
      "change_precent": "2.18",
      "last_closeRaw": "2045.09997558593750",
      "last_openRaw": "2001.05004882812500",
      "last_maxRaw": "2045.93994140625000",
      "last_minRaw": "1982.43005371093750",
      "change_precentRaw": 2.182446996709429
    },
    {
      "direction_color": "greenFont",
      "rowDate": "2008年12月17日",
      "rowDateRaw": 1229472000,
      "rowDateTimestamp": "2008-12-17T00:00:00Z",
      "last_close": "2,001.42",
      "last_open": "2,002.03",
      "last_max": "2,030.39",
      "last_min": "1,995.65",
      "volume": "58.69K",
      "volumeRaw": 58685,
      "change_precent": "0.35",
      "last_closeRaw": "2001.42004394531250",
      "last_openRaw": "2002.03002929687500",
      "last_maxRaw": "2030.39001464843750",
      "last_minRaw": "1995.65002441406250",
      "change_precentRaw": 0.3494744387715569
    },
    {
      "direction_color": "greenFont",
      "rowDate": "2008年12月16日",
      "rowDateRaw": 1229385600,
      "rowDateTimestamp": "2008-12-16T00:00:00Z",
      "last_close": "1,994.45",
      "last_open": "1,956.99",
      "last_max": "1,994.96",
      "last_min": "1,919.87",
      "volume": "47.93K",
      "volumeRaw": 47925,
      "change_precent": "0.98",
      "last_closeRaw": "1994.44995117187500",
      "last_openRaw": "1956.98999023437500",
      "last_maxRaw": "1994.95996093750000",
      "last_minRaw": "1919.86999511718750",
      "change_precentRaw": 0.9832722331778233
    },
    {
      "direction_color": "greenFont",
      "rowDate": "2008年12月15日",
      "rowDateRaw": 1229299200,
      "rowDateTimestamp": "2008-12-15T00:00:00Z",
      "last_close": "1,975.03",
      "last_open": "1,991.55",
      "last_max": "2,006.22",
      "last_min": "1,941.05",
      "volume": "50.45K",
      "volumeRaw": 50451,
      "change_precent": "0.75",
      "last_closeRaw": "1975.03002929687500",
      "last_openRaw": "1991.55004882812500",
      "last_maxRaw": "2006.21997070312500",
      "last_minRaw": "1941.05004882812500",
      "change_precentRaw": 0.7473053376168387
    },
    {
      "direction_color": "redFont",
      "rowDate": "2008年12月12日",
      "rowDateRaw": 1229040000,
      "rowDateTimestamp": "2008-12-12T00:00:00Z",
      "last_close": "1,960.38",
      "last_open": "2,027.07",
      "last_max": "2,038.18",
      "last_min": "1,936.28",
      "volume": "67.39K",
      "volumeRaw": 67387,
      "change_precent": "-4.20",
      "last_closeRaw": "1960.38000488281250",
      "last_openRaw": "2027.06994628906250",
      "last_maxRaw": "2038.18005371093750",
      "last_minRaw": "1936.28002929687500",
      "change_precentRaw": -4.200668626585778
    },
    {
      "direction_color": "redFont",
      "rowDate": "2008年12月11日",
      "rowDateRaw": 1228953600,
      "rowDateTimestamp": "2008-12-11T00:00:00Z",
      "last_close": "2,046.34",
      "last_open": "2,087.43",
      "last_max": "2,107.29",
      "last_min": "2,043.62",
      "volume": "73.56K",
      "volumeRaw": 73556,
      "change_precent": "-2.39",
      "last_closeRaw": "2046.33996582031250",
      "last_openRaw": "2087.42993164062500",
      "last_maxRaw": "2107.29003906250000",
      "last_minRaw": "2043.61999511718750",
      "change_precentRaw": -2.387434080607089
    },
    {
      "direction_color": "greenFont",
      "rowDate": "2008年12月10日",
      "rowDateRaw": 1228867200,
      "rowDateTimestamp": "2008-12-10T00:00:00Z",
      "last_close": "2,096.39",
      "last_open": "2,028.51",
      "last_max": "2,096.39",
      "last_min": "2,014.28",
      "volume": "83.27K",
      "volumeRaw": 83271,
      "change_precent": "2.72",
      "last_closeRaw": "2096.38989257812500",
      "last_openRaw": "2028.51000976562500",
      "last_maxRaw": "2096.38989257812500",
      "last_minRaw": "2014.28002929687500",
      "change_precentRaw": 2.7214110618906093
    },
    {
      "direction_color": "redFont",
      "rowDate": "2008年12月9日",
      "rowDateRaw": 1228780800,
      "rowDateTimestamp": "2008-12-09T00:00:00Z",
      "last_close": "2,040.85",
      "last_open": "2,104.12",
      "last_max": "2,107.60",
      "last_min": "2,038.07",
      "volume": "92.51K",
      "volumeRaw": 92510,
      "change_precent": "-2.59",
      "last_closeRaw": "2040.84997558593750",
      "last_openRaw": "2104.12011718750000",
      "last_maxRaw": "2107.60009765625000",
      "last_minRaw": "2038.06994628906250",
      "change_precentRaw": -2.5865884406109854
    },
    {
      "direction_color": "greenFont",
      "rowDate": "2008年12月8日",
      "rowDateRaw": 1228694400,
      "rowDateTimestamp": "2008-12-08T00:00:00Z",
      "last_close": "2,095.04",
      "last_open": "2,040.47",
      "last_max": "2,095.47",
      "last_min": "2,033.98",
      "volume": "107.61K",
      "volumeRaw": 107607,
      "change_precent": "4.07",
      "last_closeRaw": "2095.04003906250000",
      "last_openRaw": "2040.46997070312500",
      "last_maxRaw": "2095.46997070312500",
      "last_minRaw": "2033.97998046875000",
      "change_precentRaw": 4.066720313240042
    },
    {
      "direction_color": "greenFont",
      "rowDate": "2008年12月5日",
      "rowDateRaw": 1228435200,
      "rowDateTimestamp": "2008-12-05T00:00:00Z",
      "last_close": "2,013.17",
      "last_open": "1,969.74",
      "last_max": "2,014.20",
      "last_min": "1,965.09",
      "volume": "74.37K",
      "volumeRaw": 74366,
      "change_precent": "1.53",
      "last_closeRaw": "2013.17004394531250",
      "last_openRaw": "1969.73999023437500",
      "last_maxRaw": "2014.19995117187500",
      "last_minRaw": "1965.08996582031250",
      "change_precentRaw": 1.5250154778673422
    },
    {
      "direction_color": "greenFont",
      "rowDate": "2008年12月4日",
      "rowDateRaw": 1228348800,
      "rowDateTimestamp": "2008-12-04T00:00:00Z",
      "last_close": "1,982.93",
      "last_open": "1,980.44",
      "last_max": "2,046.47",
      "last_min": "1,978.14",
      "volume": "119.18K",
      "volumeRaw": 119183,
      "change_precent": "1.55",
      "last_closeRaw": "1982.93005371093750",
      "last_openRaw": "1980.43994140625000",
      "last_maxRaw": "2046.46997070312500",
      "last_minRaw": "1978.14001464843750",
      "change_precentRaw": 1.549673477065564
    },
    {
      "direction_color": "greenFont",
      "rowDate": "2008年12月3日",
      "rowDateRaw": 1228262400,
      "rowDateTimestamp": "2008-12-03T00:00:00Z",
      "last_close": "1,952.67",
      "last_open": "1,884.60",
      "last_max": "1,952.67",
      "last_min": "1,884.60",
      "volume": "85.02K",
      "volumeRaw": 85019,
      "change_precent": "4.50",
      "last_closeRaw": "1952.67004394531250",
      "last_openRaw": "1884.59997558593750",
      "last_maxRaw": "1952.67004394531250",
      "last_minRaw": "1884.59997558593750",
      "change_precentRaw": 4.497414621562304
    },
    {
      "direction_color": "greenFont",
      "rowDate": "2008年12月2日",
      "rowDateRaw": 1228176000,
      "rowDateTimestamp": "2008-12-02T00:00:00Z",
      "last_close": "1,868.63",
      "last_open": "1,821.54",
      "last_max": "1,891.13",
      "last_min": "1,814.90",
      "volume": "61.35K",
      "volumeRaw": 61350,
      "change_precent": "0.24",
      "last_closeRaw": "1868.63000488281250",
      "last_openRaw": "1821.54003906250000",
      "last_maxRaw": "1891.13000488281250",
      "last_minRaw": "1814.90002441406250",
      "change_precentRaw": 0.23763833424374226
    },
    {
      "direction_color": "greenFont",
      "rowDate": "2008年12月1日",
      "rowDateRaw": 1228089600,
      "rowDateTimestamp": "2008-12-01T00:00:00Z",
      "last_close": "1,864.20",
      "last_open": "1,823.77",
      "last_max": "1,864.30",
      "last_min": "1,799.84",
      "volume": "48.39K",
      "volumeRaw": 48386,
      "change_precent": "1.87",
      "last_closeRaw": "1864.19995117187500",
      "last_openRaw": "1823.77001953125000",
      "last_maxRaw": "1864.30004882812500",
      "last_minRaw": "1799.83996582031250",
      "change_precentRaw": 1.8733008220760798
    },
    {
      "direction_color": "redFont",
      "rowDate": "2008年11月28日",
      "rowDateRaw": 1227830400,
      "rowDateTimestamp": "2008-11-28T00:00:00Z",
      "last_close": "1,829.92",
      "last_open": "1,851.10",
      "last_max": "1,866.26",
      "last_min": "1,815.45",
      "volume": "51.59K",
      "volumeRaw": 51591,
      "change_precent": "-2.17",
      "last_closeRaw": "1829.92004394531250",
      "last_openRaw": "1851.09997558593750",
      "last_maxRaw": "1866.26000976562500",
      "last_minRaw": "1815.44995117187500",
      "change_precentRaw": -2.167900441757397
    },
    {
      "direction_color": "greenFont",
      "rowDate": "2008年11月27日",
      "rowDateRaw": 1227744000,
      "rowDateTimestamp": "2008-11-27T00:00:00Z",
      "last_close": "1,870.47",
      "last_open": "1,961.89",
      "last_max": "1,969.02",
      "last_min": "1,870.05",
      "volume": "88.01K",
      "volumeRaw": 88008,
      "change_precent": "1.46",
      "last_closeRaw": "1870.46997070312500",
      "last_openRaw": "1961.89001464843750",
      "last_maxRaw": "1969.02001953125000",
      "last_minRaw": "1870.05004882812500",
      "change_precentRaw": 1.463527364491947
    },
    {
      "direction_color": "greenFont",
      "rowDate": "2008年11月26日",
      "rowDateRaw": 1227657600,
      "rowDateTimestamp": "2008-11-26T00:00:00Z",
      "last_close": "1,843.49",
      "last_open": "1,832.11",
      "last_max": "1,865.65",
      "last_min": "1,815.02",
      "volume": "45.57K",
      "volumeRaw": 45566,
      "change_precent": "0.50",
      "last_closeRaw": "1843.48999023437500",
      "last_openRaw": "1832.10998535156250",
      "last_maxRaw": "1865.65002441406250",
      "last_minRaw": "1815.02001953125000",
      "change_precentRaw": 0.501553787893711
    },
    {
      "direction_color": "redFont",
      "rowDate": "2008年11月25日",
      "rowDateRaw": 1227571200,
      "rowDateTimestamp": "2008-11-25T00:00:00Z",
      "last_close": "1,834.29",
      "last_open": "1,870.06",
      "last_max": "1,883.10",
      "last_min": "1,801.56",
      "volume": "42.82K",
      "volumeRaw": 42815,
      "change_precent": "-0.18",
      "last_closeRaw": "1834.29003906250000",
      "last_openRaw": "1870.06005859375000",
      "last_maxRaw": "1883.09997558593750",
      "last_minRaw": "1801.56005859375000",
      "change_precentRaw": -0.18229770571133272
    },
    {
      "direction_color": "redFont",
      "rowDate": "2008年11月24日",
      "rowDateRaw": 1227484800,
      "rowDateTimestamp": "2008-11-24T00:00:00Z",
      "last_close": "1,837.64",
      "last_open": "1,913.99",
      "last_max": "1,923.93",
      "last_min": "1,835.86",
      "volume": "50.56K",
      "volumeRaw": 50562,
      "change_precent": "-4.33",
      "last_closeRaw": "1837.64001464843750",
      "last_openRaw": "1913.98999023437500",
      "last_maxRaw": "1923.93005371093750",
      "last_minRaw": "1835.85998535156250",
      "change_precentRaw": -4.325957665326522
    },
    {
      "direction_color": "redFont",
      "rowDate": "2008年11月21日",
      "rowDateRaw": 1227225600,
      "rowDateTimestamp": "2008-11-21T00:00:00Z",
      "last_close": "1,920.73",
      "last_open": "1,872.27",
      "last_max": "1,968.89",
      "last_min": "1,835.09",
      "volume": "83.05K",
      "volumeRaw": 83049,
      "change_precent": "-0.61",
      "last_closeRaw": "1920.72998046875000",
      "last_openRaw": "1872.27001953125000",
      "last_maxRaw": "1968.89001464843750",
      "last_minRaw": "1835.08996582031250",
      "change_precentRaw": -0.6054590808976135
    },
    {
      "direction_color": "redFont",
      "rowDate": "2008年11月20日",
      "rowDateRaw": 1227139200,
      "rowDateTimestamp": "2008-11-20T00:00:00Z",
      "last_close": "1,932.43",
      "last_open": "1,916.70",
      "last_max": "1,976.95",
      "last_min": "1,900.27",
      "volume": "83.19K",
      "volumeRaw": 83187,
      "change_precent": "-1.06",
      "last_closeRaw": "1932.43005371093750",
      "last_openRaw": "1916.69995117187500",
      "last_maxRaw": "1976.94995117187500",
      "last_minRaw": "1900.27001953125000",
      "change_precentRaw": -1.0613559619274329
    },
    {
      "direction_color": "greenFont",
      "rowDate": "2008年11月19日",
      "rowDateRaw": 1227052800,
      "rowDateTimestamp": "2008-11-19T00:00:00Z",
      "last_close": "1,953.16",
      "last_open": "1,831.60",
      "last_max": "1,959.52",
      "last_min": "1,823.27",
      "volume": "82.12K",
      "volumeRaw": 82117,
      "change_precent": "6.16",
      "last_closeRaw": "1953.16003417968750",
      "last_openRaw": "1831.59997558593750",
      "last_maxRaw": "1959.52001953125000",
      "last_minRaw": "1823.27001953125000",
      "change_precentRaw": 6.160390212054893
    },
    {
      "direction_color": "redFont",
      "rowDate": "2008年11月18日",
      "rowDateRaw": 1226966400,
      "rowDateTimestamp": "2008-11-18T00:00:00Z",
      "last_close": "1,839.82",
      "last_open": "1,974.38",
      "last_max": "1,994.82",
      "last_min": "1,831.76",
      "volume": "97.28K",
      "volumeRaw": 97278,
      "change_precent": "-7.42",
      "last_closeRaw": "1839.81994628906250",
      "last_openRaw": "1974.38000488281250",
      "last_maxRaw": "1994.81994628906250",
      "last_minRaw": "1831.76000976562500",
      "change_precentRaw": -7.41739850580854
    },
    {
      "direction_color": "greenFont",
      "rowDate": "2008年11月17日",
      "rowDateRaw": 1226880000,
      "rowDateTimestamp": "2008-11-17T00:00:00Z",
      "last_close": "1,987.22",
      "last_open": "1,934.74",
      "last_max": "1,987.22",
      "last_min": "1,919.97",
      "volume": "87.84K",
      "volumeRaw": 87837,
      "change_precent": "2.24",
      "last_closeRaw": "1987.21997070312500",
      "last_openRaw": "1934.73999023437500",
      "last_maxRaw": "1987.21997070312500",
      "last_minRaw": "1919.96997070312500",
      "change_precentRaw": 2.241655943291396
    },
    {
      "direction_color": "greenFont",
      "rowDate": "2008年11月14日",
      "rowDateRaw": 1226620800,
      "rowDateTimestamp": "2008-11-14T00:00:00Z",
      "last_close": "1,943.65",
      "last_open": "1,893.31",
      "last_max": "1,943.65",
      "last_min": "1,874.93",
      "volume": "91.17K",
      "volumeRaw": 91169,
      "change_precent": "3.71",
      "last_closeRaw": "1943.65002441406250",
      "last_openRaw": "1893.31005859375000",
      "last_maxRaw": "1943.65002441406250",
      "last_minRaw": "1874.93005371093750",
      "change_precentRaw": 3.7122251980024314
    },
    {
      "direction_color": "greenFont",
      "rowDate": "2008年11月13日",
      "rowDateRaw": 1226534400,
      "rowDateTimestamp": "2008-11-13T00:00:00Z",
      "last_close": "1,874.08",
      "last_open": "1,777.03",
      "last_max": "1,891.94",
      "last_min": "1,765.63",
      "volume": "83.24K",
      "volumeRaw": 83235,
      "change_precent": "4.01",
      "last_closeRaw": "1874.07995605468750",
      "last_openRaw": "1777.03002929687500",
      "last_maxRaw": "1891.93994140625000",
      "last_minRaw": "1765.63000488281250",
      "change_precentRaw": 4.010390156599613
    },
    {
      "direction_color": "greenFont",
      "rowDate": "2008年11月12日",
      "rowDateRaw": 1226448000,
      "rowDateTimestamp": "2008-11-12T00:00:00Z",
      "last_close": "1,801.82",
      "last_open": "1,758.48",
      "last_max": "1,806.23",
      "last_min": "1,754.29",
      "volume": "44.09K",
      "volumeRaw": 44088,
      "change_precent": "1.15",
      "last_closeRaw": "1801.81994628906250",
      "last_openRaw": "1758.47998046875000",
      "last_maxRaw": "1806.22998046875000",
      "last_minRaw": "1754.29003906250000",
      "change_precentRaw": 1.148558466887427
    },
    {
      "direction_color": "redFont",
      "rowDate": "2008年11月11日",
      "rowDateRaw": 1226361600,
      "rowDateTimestamp": "2008-11-11T00:00:00Z",
      "last_close": "1,781.36",
      "last_open": "1,795.30",
      "last_max": "1,824.93",
      "last_min": "1,778.33",
      "volume": "66.07K",
      "volumeRaw": 66073,
      "change_precent": "-1.13",
      "last_closeRaw": "1781.35998535156250",
      "last_openRaw": "1795.30004882812500",
      "last_maxRaw": "1824.93005371093750",
      "last_minRaw": "1778.32995605468750",
      "change_precentRaw": -1.1267413631322405
    },
    {
      "direction_color": "greenFont",
      "rowDate": "2008年11月10日",
      "rowDateRaw": 1226275200,
      "rowDateTimestamp": "2008-11-10T00:00:00Z",
      "last_close": "1,801.66",
      "last_open": "1,714.12",
      "last_max": "1,803.12",
      "last_min": "1,714.12",
      "volume": "63.95K",
      "volumeRaw": 63949,
      "change_precent": "7.38",
      "last_closeRaw": "1801.66003417968750",
      "last_openRaw": "1714.11999511718750",
      "last_maxRaw": "1803.11999511718750",
      "last_minRaw": "1714.11999511718750",
      "change_precentRaw": 7.380371156096098
    },
    {
      "direction_color": "greenFont",
      "rowDate": "2008年11月7日",
      "rowDateRaw": 1226016000,
      "rowDateTimestamp": "2008-11-07T00:00:00Z",
      "last_close": "1,677.83",
      "last_open": "1,618.75",
      "last_max": "1,690.11",
      "last_min": "1,612.74",
      "volume": "31.52K",
      "volumeRaw": 31522,
      "change_precent": "1.70",
      "last_closeRaw": "1677.82995605468750",
      "last_openRaw": "1618.75000000000000",
      "last_maxRaw": "1690.10998535156250",
      "last_minRaw": "1612.73999023437500",
      "change_precentRaw": 1.700222227187899
    },
    {
      "direction_color": "redFont",
      "rowDate": "2008年11月6日",
      "rowDateRaw": 1225929600,
      "rowDateTimestamp": "2008-11-06T00:00:00Z",
      "last_close": "1,649.78",
      "last_open": "1,648.13",
      "last_max": "1,661.44",
      "last_min": "1,638.34",
      "volume": "30.78K",
      "volumeRaw": 30784,
      "change_precent": "-2.46",
      "last_closeRaw": "1649.78002929687500",
      "last_openRaw": "1648.13000488281250",
      "last_maxRaw": "1661.43994140625000",
      "last_minRaw": "1638.33996582031250",
      "change_precentRaw": -2.4618376019306423
    },
    {
      "direction_color": "greenFont",
      "rowDate": "2008年11月5日",
      "rowDateRaw": 1225843200,
      "rowDateTimestamp": "2008-11-05T00:00:00Z",
      "last_close": "1,691.42",
      "last_open": "1,641.26",
      "last_max": "1,714.66",
      "last_min": "1,641.26",
      "volume": "42.42K",
      "volumeRaw": 42418,
      "change_precent": "3.91",
      "last_closeRaw": "1691.42004394531250",
      "last_openRaw": "1641.26000976562500",
      "last_maxRaw": "1714.66003417968750",
      "last_minRaw": "1641.26000976562500",
      "change_precentRaw": 3.9108980315134825
    },
    {
      "direction_color": "redFont",
      "rowDate": "2008年11月4日",
      "rowDateRaw": 1225756800,
      "rowDateTimestamp": "2008-11-04T00:00:00Z",
      "last_close": "1,627.76",
      "last_open": "1,646.20",
      "last_max": "1,648.45",
      "last_min": "1,606.73",
      "volume": "26.10K",
      "volumeRaw": 26100,
      "change_precent": "-1.56",
      "last_closeRaw": "1627.76000976562500",
      "last_openRaw": "1646.19995117187500",
      "last_maxRaw": "1648.44995117187500",
      "last_minRaw": "1606.72998046875000",
      "change_precentRaw": -1.559081043570701
    },
    {
      "direction_color": "redFont",
      "rowDate": "2008年11月3日",
      "rowDateRaw": 1225670400,
      "rowDateTimestamp": "2008-11-03T00:00:00Z",
      "last_close": "1,653.54",
      "last_open": "1,648.56",
      "last_max": "1,684.56",
      "last_min": "1,643.42",
      "volume": "25.38K",
      "volumeRaw": 25381,
      "change_precent": "-0.61",
      "last_closeRaw": "1653.54003906250000",
      "last_openRaw": "1648.56005859375000",
      "last_maxRaw": "1684.56005859375000",
      "last_minRaw": "1643.42004394531250",
      "change_precentRaw": -0.6082970624570805
    }
  ]
}